odoo10_addon_calendar_event_kanban_stage-10.0.1.0.0-py2.7-nspkg.pth
odoo/addons/calendar_event_kanban_stage/README.rst
odoo/addons/calendar_event_kanban_stage/__init__.py
odoo/addons/calendar_event_kanban_stage/__manifest__.py
odoo/addons/calendar_event_kanban_stage/data/base_kanban_stage_data.xml
odoo/addons/calendar_event_kanban_stage/models/__init__.py
odoo/addons/calendar_event_kanban_stage/models/calendar_event.py
odoo/addons/calendar_event_kanban_stage/static/description/icon.png
odoo/addons/calendar_event_kanban_stage/views/calendar_event_view.xml
odoo10_addon_calendar_event_kanban_stage-10.0.1.0.0.dist-info/DESCRIPTION.rst
odoo10_addon_calendar_event_kanban_stage-10.0.1.0.0.dist-info/METADATA
odoo10_addon_calendar_event_kanban_stage-10.0.1.0.0.dist-info/RECORD
odoo10_addon_calendar_event_kanban_stage-10.0.1.0.0.dist-info/WHEEL
odoo10_addon_calendar_event_kanban_stage-10.0.1.0.0.dist-info/metadata.json
odoo10_addon_calendar_event_kanban_stage-10.0.1.0.0.dist-info/namespace_packages.txt
odoo10_addon_calendar_event_kanban_stage-10.0.1.0.0.dist-info/top_level.txt
